{
  "animateLoading": true,
  "borderRadius": "{{appsmith.theme.borderRadius.appBorderRadius}}",
  "bottomRow": 4,
  "displayName": "Text",
  "dynamicBindingPathList": [
    {
      "key": "truncateButtonColor"
    },
    {
      "key": "fontFamily"
    },
    {
      "key": "borderRadius"
    }
  ],
  "dynamicHeight": "FIXED",
  "dynamicTriggerPathList": [],
  "fontFamily": "{{appsmith.theme.fontFamily.appFont}}",
  "fontSize": "1.875rem",
  "fontStyle": "BOLD",
  "hideCard": false,
  "iconSVG": "https://appcdn.appsmith.com/static/media/icon.a47d6d5dbbb718c4dc4b2eb4f218c1b7.svg",
  "isDeprecated": false,
  "isLoading": false,
  "isVisible": true,
  "key": "wp8ijwfpam",
  "leftColumn": 0,
  "maxDynamicHeight": 9000,
  "minDynamicHeight": 4,
  "minWidth": 450,
  "mobileBottomRow": 8,
  "mobileLeftColumn": 5,
  "mobileRightColumn": 21,
  "mobileTopRow": 4,
  "overflow": "NONE",
  "parentColumnSpace": 20.75,
  "parentId": "nyy2t4rpxe",
  "parentRowSpace": 10,
  "renderMode": "CANVAS",
  "responsiveBehavior": "fill",
  "rightColumn": 57,
  "searchTags": [
    "typography",
    "paragraph",
    "label"
  ],
  "shouldTruncate": false,
  "tags": [
    "Suggested",
    "Content"
  ],
  "text": "Candidates",
  "textAlign": "LEFT",
  "textColor": "#231F20",
  "topRow": 0,
  "truncateButtonColor": "{{appsmith.theme.colors.primaryColor}}",
  "type": "TEXT_WIDGET",
  "version": 1,
  "widgetId": "f5bh8frgf4",
  "widgetName": "txt_title"
}